Metadata-Version: 2.1
Name: cotylab
Version: 1.0
Summary: 컴퓨팅 사고력 교육을 위한 오픈소스
Home-page: https://github.com/misoncorp/cotylab
Author: cotylab
Author-email: misoncorp@gmail.com
License: MIT
Platform: UNKNOWN
License-File: LICENSE
